randomyoutubevideo/__init__.py
randomyoutubevideo-1.0.1.dist-info/METADATA
randomyoutubevideo-1.0.1.dist-info/WHEEL
randomyoutubevideo-1.0.1.dist-info/top_level.txt
randomyoutubevideo-1.0.1.dist-info/RECORD
