Metadata-Version: 2.1
Name: randomyoutubevideo
Version: 1.0.1
Author: emresvd
Classifier: Development Status :: 5 - Production/Stable
Classifier: Intended Audience :: Developers
Classifier: Natural Language :: English
Classifier: Programming Language :: Python :: 3.7
Classifier: Topic :: Software Development :: Libraries :: Python Modules
Requires-Dist: beautifulsoup4 (==4.11.1)
Requires-Dist: requests (==2.28.1)
Requires-Dist: youtube-search (==1.1.1)
Requires-Dist: youtube-search-python (==1.4.2)
